OfflineSandbox.py
t.py
tests.py
offline_sandbox-1.dist-info/DESCRIPTION.rst
offline_sandbox-1.dist-info/METADATA
offline_sandbox-1.dist-info/RECORD
offline_sandbox-1.dist-info/WHEEL
offline_sandbox-1.dist-info/metadata.json
offline_sandbox-1.dist-info/top_level.txt
