Metadata-Version: 1.0
Name: offline_sandbox
Version: 1
Summary: Decorator to return a default value for a function when offline
Home-page: https://github.com/jadolg/offline_sandbox
Author: Jorge Alberto Díaz Orozco
Author-email: diazorozcoj@gmail.com
License: MIT
Platform: UNKNOWN
